aioalice/__init__.py
aioalice/dispatcher/__init__.py
aioalice/dispatcher/api.py
aioalice/dispatcher/filters.py
aioalice/dispatcher/handler.py
aioalice/dispatcher/storage.py
aioalice/dispatcher/webhook.py
aioalice/types/__init__.py
aioalice/types/alice_request.py
aioalice/types/alice_response.py
aioalice/types/base.py
aioalice/types/button.py
aioalice/types/card.py
aioalice/types/card_footer.py
aioalice/types/card_header.py
aioalice/types/entity.py
aioalice/types/entity_tokens.py
aioalice/types/entity_value.py
aioalice/types/image.py
aioalice/types/interfaces.py
aioalice/types/markup.py
aioalice/types/media_button.py
aioalice/types/meta.py
aioalice/types/natural_language_understanding.py
aioalice/types/quota.py
aioalice/types/request.py
aioalice/types/response.py
aioalice/types/session.py
aioalice/types/uploaded_image.py
aioalice/utils/__init__.py
aioalice/utils/exceptions.py
aioalice/utils/helper.py
aioalice/utils/json.py
aioalice/utils/payload.py
aioalice/utils/safe_kwargs.py
aioAlice-1.5.1.dist-info/LICENSE
aioAlice-1.5.1.dist-info/METADATA
aioAlice-1.5.1.dist-info/WHEEL
aioAlice-1.5.1.dist-info/top_level.txt
aioAlice-1.5.1.dist-info/RECORD
