Metadata-Version: 2.1
Name: aioAlice
Version: 1.5.1
Summary: Asynchronous library for Yandex Dialogs (Alice) API
Home-page: https://github.com/mahenzon/aioalice
Author: Suren Khorenyan
Author-email: surenkhorenyan@gmail.com
License: MIT
Platform: UNKNOWN
Classifier: Development Status :: 5 - Production/Stable
Classifier: Environment :: Console
Classifier: Framework :: AsyncIO
Classifier: Intended Audience :: Developers
Classifier: Intended Audience :: System Administrators
Classifier: License :: OSI Approved :: MIT License
Classifier: Programming Language :: Python :: 3.6
Classifier: Topic :: Software Development :: Libraries :: Application Frameworks
Requires-Dist: aiohttp (>=3.3.2)
Requires-Dist: attrs (==20.3.0)
